{
  "porto": "PORTO DO RIO GRANDE (ESTADO DO RIO GRANDE DO SUL) - 2025 173",
  "ano": 2025,
  "eventos": [
    {
      "data": "2025-02-01",
      "mares": [
        {
          "hora": "05:10",
          "altura_m": 0.27
        },
        {
          "hora": "04:36",
          "altura_m": 0.28
        },
        {
          "hora": "03:12",
          "altura_m": 0.16
        }
      ]
    },
    {
      "data": "2025-02-02",
      "mares": [
        {
          "hora": "02:53",
          "altura_m": 0.12
        },
        {
          "hora": "05:06",
          "altura_m": 0.22
        },
        {
          "hora": "06:02",
          "altura_m": 0.18
        }
      ]
    },
    {
      "data": "2025-02-03",
      "mares": [
        {
          "hora": "00:21",
          "altura_m": 0.19
        },
        {
          "hora": "03:08",
          "altura_m": 0.05
        },
        {
          "hora": "00:25",
          "altura_m": 0.34
        }
      ]
    },
    {
      "data": "2025-02-04",
      "mares": [
        {
          "hora": "00:44",
          "altura_m": 0.24
        },
        {
          "hora": "00:02",
          "altura_m": 0.32
        },
        {
          "hora": "00:53",
          "altura_m": 0.38
        }
      ]
    },
    {
      "data": "2025-02-06",
      "mares": [
        {
          "hora": "05:59",
          "altura_m": 0.14
        },
        {
          "hora": "06:19",
          "altura_m": 0.05
        },
        {
          "hora": "06:59",
          "altura_m": 0.14
        }
      ]
    },
    {
      "data": "2025-02-10",
      "mares": [
        {
          "hora": "09:44",
          "altura_m": 0.17
        },
        {
          "hora": "03:04",
          "altura_m": 0.35
        },
        {
          "hora": "10:25",
          "altura_m": 0.18
        }
      ]
    },
    {
      "data": "2025-02-11",
      "mares": [
        {
          "hora": "02:12",
          "altura_m": 0.38
        },
        {
          "hora": "02:04",
          "altura_m": 0.4
        },
        {
          "hora": "02:42",
          "altura_m": 0.38
        }
      ]
    },
    {
      "data": "2025-02-12",
      "mares": [
        {
          "hora": "02:27",
          "altura_m": 0.39
        },
        {
          "hora": "02:49",
          "altura_m": 0.36
        },
        {
          "hora": "03:02",
          "altura_m": 0.33
        }
      ]
    },
    {
      "data": "2025-02-14",
      "mares": [
        {
          "hora": "05:04",
          "altura_m": 0.33
        },
        {
          "hora": "04:01",
          "altura_m": 0.3
        }
      ]
    },
    {
      "data": "2025-02-15",
      "mares": [
        {
          "hora": "04:02",
          "altura_m": 0.32
        },
        {
          "hora": "00:01",
          "altura_m": 0.15
        }
      ]
    },
    {
      "data": "2025-02-16",
      "mares": [
        {
          "hora": "02:27",
          "altura_m": 0.16
        }
      ]
    },
    {
      "data": "2025-03-01",
      "mares": [
        {
          "hora": "03:25",
          "altura_m": 0.29
        },
        {
          "hora": "02:01",
          "altura_m": 0.18
        }
      ]
    },
    {
      "data": "2025-03-02",
      "mares": [
        {
          "hora": "04:02",
          "altura_m": 0.23
        },
        {
          "hora": "04:51",
          "altura_m": 0.22
        }
      ]
    },
    {
      "data": "2025-03-03",
      "mares": [
        {
          "hora": "02:02",
          "altura_m": 0.05
        },
        {
          "hora": "03:29",
          "altura_m": 0.17
        }
      ]
    },
    {
      "data": "2025-03-04",
      "mares": [
        {
          "hora": "03:06",
          "altura_m": 0.05
        },
        {
          "hora": "04:12",
          "altura_m": 0.16
        }
      ]
    },
    {
      "data": "2025-03-06",
      "mares": [
        {
          "hora": "05:12",
          "altura_m": 0.05
        },
        {
          "hora": "05:49",
          "altura_m": 0.12
        }
      ]
    },
    {
      "data": "2025-03-10",
      "mares": [
        {
          "hora": "04:47",
          "altura_m": 0.5
        },
        {
          "hora": "08:38",
          "altura_m": 0.17
        }
      ]
    },
    {
      "data": "2025-03-11",
      "mares": [
        {
          "hora": "01:04",
          "altura_m": 0.38
        },
        {
          "hora": "05:04",
          "altura_m": 0.43
        }
      ]
    },
    {
      "data": "2025-03-12",
      "mares": [
        {
          "hora": "01:44",
          "altura_m": 0.35
        },
        {
          "hora": "02:04",
          "altura_m": 0.33
        }
      ]
    },
    {
      "data": "2025-03-14",
      "mares": [
        {
          "hora": "02:53",
          "altura_m": 0.3
        },
        {
          "hora": "02:59",
          "altura_m": 0.22
        }
      ]
    },
    {
      "data": "2025-03-15",
      "mares": [
        {
          "hora": "03:16",
          "altura_m": 0.28
        },
        {
          "hora": "00:53",
          "altura_m": 0.03
        }
      ]
    },
    {
      "data": "2025-03-16",
      "mares": [
        {
          "hora": "01:02",
          "altura_m": 0.17
        }
      ]
    },
    {
      "data": "2025-04-01",
      "mares": [
        {
          "hora": "02:01",
          "altura_m": 0.04
        },
        {
          "hora": "03:02",
          "altura_m": 0.18
        }
      ]
    },
    {
      "data": "2025-04-02",
      "mares": [
        {
          "hora": "04:46",
          "altura_m": 0.11
        },
        {
          "hora": "05:21",
          "altura_m": 0.18
        }
      ]
    },
    {
      "data": "2025-04-03",
      "mares": [
        {
          "hora": "04:02",
          "altura_m": 0.06
        },
        {
          "hora": "06:02",
          "altura_m": 0.17
        }
      ]
    },
    {
      "data": "2025-04-04",
      "mares": [
        {
          "hora": "00:25",
          "altura_m": 0.6
        },
        {
          "hora": "00:12",
          "altura_m": 0.48
        }
      ]
    },
    {
      "data": "2025-04-05",
      "mares": [
        {
          "hora": "01:21",
          "altura_m": 0.61
        },
        {
          "hora": "00:49",
          "altura_m": 0.49
        }
      ]
    },
    {
      "data": "2025-04-07",
      "mares": [
        {
          "hora": "03:27",
          "altura_m": 0.52
        },
        {
          "hora": "02:21",
          "altura_m": 0.48
        }
      ]
    },
    {
      "data": "2025-04-10",
      "mares": [
        {
          "hora": "03:53",
          "altura_m": 0.18
        },
        {
          "hora": "03:02",
          "altura_m": 0.22
        }
      ]
    },
    {
      "data": "2025-04-11",
      "mares": [
        {
          "hora": "01:44",
          "altura_m": 0.29
        },
        {
          "hora": "01:51",
          "altura_m": 0.2
        }
      ]
    },
    {
      "data": "2025-04-12",
      "mares": [
        {
          "hora": "02:08",
          "altura_m": 0.28
        },
        {
          "hora": "02:16",
          "altura_m": 0.17
        }
      ]
    },
    {
      "data": "2025-04-14",
      "mares": [
        {
          "hora": "00:51",
          "altura_m": 0.18
        },
        {
          "hora": "01:47",
          "altura_m": 0.05
        }
      ]
    },
    {
      "data": "2025-04-15",
      "mares": [
        {
          "hora": "01:34",
          "altura_m": 0.18
        }
      ]
    },
    {
      "data": "2025-04-16",
      "mares": [
        {
          "hora": "02:12",
          "altura_m": 0.18
        }
      ]
    },
    {
      "data": "2025-05-01",
      "mares": [
        {
          "hora": "02:44",
          "altura_m": 0.08
        },
        {
          "hora": "03:16",
          "altura_m": 0.18
        }
      ]
    },
    {
      "data": "2025-05-04",
      "mares": [
        {
          "hora": "01:12",
          "altura_m": 0.6
        },
        {
          "hora": "00:40",
          "altura_m": 0.49
        }
      ]
    },
    {
      "data": "2025-05-05",
      "mares": [
        {
          "hora": "02:14",
          "altura_m": 0.55
        },
        {
          "hora": "01:31",
          "altura_m": 0.49
        }
      ]
    },
    {
      "data": "2025-05-07",
      "mares": [
        {
          "hora": "00:42",
          "altura_m": 0.26
        },
        {
          "hora": "03:38",
          "altura_m": 0.43
        }
      ]
    },
    {
      "data": "2025-05-08",
      "mares": [
        {
          "hora": "02:17",
          "altura_m": 0.2
        },
        {
          "hora": "00:55",
          "altura_m": 0.2
        }
      ]
    },
    {
      "data": "2025-05-10",
      "mares": [
        {
          "hora": "04:19",
          "altura_m": 0.09
        },
        {
          "hora": "03:32",
          "altura_m": 0.05
        }
      ]
    },
    {
      "data": "2025-05-11",
      "mares": [
        {
          "hora": "01:29",
          "altura_m": 0.27
        },
        {
          "hora": "01:53",
          "altura_m": 0.14
        }
      ]
    },
    {
      "data": "2025-05-12",
      "mares": [
        {
          "hora": "02:02",
          "altura_m": 0.28
        },
        {
          "hora": "00:25",
          "altura_m": 0.05
        }
      ]
    },
    {
      "data": "2025-05-14",
      "mares": [
        {
          "hora": "01:02",
          "altura_m": 0.19
        },
        {
          "hora": "02:14",
          "altura_m": 0.15
        }
      ]
    },
    {
      "data": "2025-05-16",
      "mares": [
        {
          "hora": "02:40",
          "altura_m": 0.18
        }
      ]
    },
    {
      "data": "2025-06-01",
      "mares": [
        {
          "hora": "00:02",
          "altura_m": 0.59
        },
        {
          "hora": "04:08",
          "altura_m": 0.19
        }
      ]
    },
    {
      "data": "2025-06-04",
      "mares": [
        {
          "hora": "03:06",
          "altura_m": 0.43
        },
        {
          "hora": "02:32",
          "altura_m": 0.45
        }
      ]
    },
    {
      "data": "2025-06-07",
      "mares": [
        {
          "hora": "03:04",
          "altura_m": 0.15
        },
        {
          "hora": "01:57",
          "altura_m": 0.05
        }
      ]
    },
    {
      "data": "2025-06-08",
      "mares": [
        {
          "hora": "00:08",
          "altura_m": 0.24
        },
        {
          "hora": "00:27",
          "altura_m": 0.12
        }
      ]
    },
    {
      "data": "2025-06-10",
      "mares": [
        {
          "hora": "05:44",
          "altura_m": 0.04
        },
        {
          "hora": "02:06",
          "altura_m": 0.18
        }
      ]
    },
    {
      "data": "2025-06-11",
      "mares": [
        {
          "hora": "02:12",
          "altura_m": 0.28
        },
        {
          "hora": "01:02",
          "altura_m": 0.17
        }
      ]
    },
    {
      "data": "2025-06-12",
      "mares": [
        {
          "hora": "00:42",
          "altura_m": 0.19
        },
        {
          "hora": "01:59",
          "altura_m": 0.22
        }
      ]
    },
    {
      "data": "2025-06-14",
      "mares": [
        {
          "hora": "02:04",
          "altura_m": 0.19
        },
        {
          "hora": "00:01",
          "altura_m": 0.52
        }
      ]
    },
    {
      "data": "2025-06-16",
      "mares": [
        {
          "hora": "03:27",
          "altura_m": 0.19
        }
      ]
    },
    {
      "data": "2025-06-29",
      "mares": [
        {
          "hora": "02:53",
          "altura_m": 0.19
        }
      ]
    },
    {
      "data": "2025-07-01",
      "mares": [
        {
          "hora": "01:02",
          "altura_m": 0.49
        },
        {
          "hora": "00:47",
          "altura_m": 0.47
        }
      ]
    },
    {
      "data": "2025-07-04",
      "mares": [
        {
          "hora": "03:36",
          "altura_m": 0.29
        },
        {
          "hora": "03:10",
          "altura_m": 0.36
        }
      ]
    },
    {
      "data": "2025-07-06",
      "mares": [
        {
          "hora": "03:01",
          "altura_m": 0.16
        },
        {
          "hora": "01:40",
          "altura_m": 0.04
        }
      ]
    },
    {
      "data": "2025-07-07",
      "mares": [
        {
          "hora": "04:51",
          "altura_m": 0.1
        },
        {
          "hora": "00:02",
          "altura_m": 0.15
        }
      ]
    },
    {
      "data": "2025-07-08",
      "mares": [
        {
          "hora": "00:23",
          "altura_m": 0.24
        },
        {
          "hora": "01:02",
          "altura_m": 0.2
        }
      ]
    },
    {
      "data": "2025-07-10",
      "mares": [
        {
          "hora": "06:25",
          "altura_m": 0.02
        },
        {
          "hora": "02:44",
          "altura_m": 0.31
        }
      ]
    },
    {
      "data": "2025-07-11",
      "mares": [
        {
          "hora": "00:06",
          "altura_m": 0.2
        },
        {
          "hora": "01:31",
          "altura_m": 0.3
        }
      ]
    },
    {
      "data": "2025-07-12",
      "mares": [
        {
          "hora": "00:53",
          "altura_m": 0.2
        },
        {
          "hora": "02:19",
          "altura_m": 0.32
        }
      ]
    },
    {
      "data": "2025-07-14",
      "mares": [
        {
          "hora": "02:10",
          "altura_m": 0.22
        },
        {
          "hora": "01:02",
          "altura_m": 0.42
        }
      ]
    },
    {
      "data": "2025-07-16",
      "mares": [
        {
          "hora": "03:47",
          "altura_m": 0.23
        }
      ]
    },
    {
      "data": "2025-08-17",
      "mares": [
        {
          "hora": "02:06",
          "altura_m": 0.38
        }
      ]
    },
    {
      "data": "2025-08-20",
      "mares": [
        {
          "hora": "01:44",
          "altura_m": 0.05
        }
      ]
    },
    {
      "data": "2025-08-23",
      "mares": [
        {
          "hora": "01:40",
          "altura_m": 0.33
        }
      ]
    },
    {
      "data": "2025-08-24",
      "mares": [
        {
          "hora": "00:12",
          "altura_m": 0.3
        }
      ]
    },
    {
      "data": "2025-08-26",
      "mares": [
        {
          "hora": "03:55",
          "altura_m": 0.4
        }
      ]
    },
    {
      "data": "2025-08-27",
      "mares": [
        {
          "hora": "00:21",
          "altura_m": 0.38
        }
      ]
    },
    {
      "data": "2025-08-28",
      "mares": [
        {
          "hora": "01:04",
          "altura_m": 0.33
        }
      ]
    },
    {
      "data": "2025-08-30",
      "mares": [
        {
          "hora": "01:47",
          "altura_m": 0.26
        }
      ]
    },
    {
      "data": "2025-10-01",
      "mares": [
        {
          "hora": "23:36",
          "altura_m": 0.21
        }
      ]
    },
    {
      "data": "2025-10-03",
      "mares": [
        {
          "hora": "03:17",
          "altura_m": 0.04
        },
        {
          "hora": "06:06",
          "altura_m": 0.01
        },
        {
          "hora": "00:04",
          "altura_m": 0.36
        }
      ]
    },
    {
      "data": "2025-10-04",
      "mares": [
        {
          "hora": "00:25",
          "altura_m": 0.33
        },
        {
          "hora": "06:59",
          "altura_m": -0.01
        },
        {
          "hora": "01:01",
          "altura_m": 0.4
        }
      ]
    },
    {
      "data": "2025-10-05",
      "mares": [
        {
          "hora": "00:34",
          "altura_m": 0.31
        },
        {
          "hora": "01:53",
          "altura_m": 0.4
        }
      ]
    },
    {
      "data": "2025-10-06",
      "mares": [
        {
          "hora": "05:47",
          "altura_m": 0.05
        }
      ]
    },
    {
      "data": "2025-10-07",
      "mares": [
        {
          "hora": "00:40",
          "altura_m": 0.33
        },
        {
          "hora": "01:55",
          "altura_m": 0.4
        },
        {
          "hora": "03:04",
          "altura_m": 0.36
        }
      ]
    },
    {
      "data": "2025-10-08",
      "mares": [
        {
          "hora": "00:01",
          "altura_m": 0.33
        },
        {
          "hora": "02:38",
          "altura_m": 0.41
        },
        {
          "hora": "03:49",
          "altura_m": 0.33
        }
      ]
    },
    {
      "data": "2025-10-10",
      "mares": [
        {
          "hora": "04:51",
          "altura_m": 0.32
        },
        {
          "hora": "04:06",
          "altura_m": 0.39
        },
        {
          "hora": "07:02",
          "altura_m": 0.23
        }
      ]
    },
    {
      "data": "2025-10-11",
      "mares": [
        {
          "hora": "02:59",
          "altura_m": 0.23
        },
        {
          "hora": "02:29",
          "altura_m": 0.18
        },
        {
          "hora": "02:46",
          "altura_m": 0.18
        }
      ]
    },
    {
      "data": "2025-10-12",
      "mares": [
        {
          "hora": "01:27",
          "altura_m": 0.21
        },
        {
          "hora": "00:02",
          "altura_m": 0.32
        },
        {
          "hora": "01:17",
          "altura_m": 0.17
        }
      ]
    },
    {
      "data": "2025-10-14",
      "mares": [
        {
          "hora": "01:25",
          "altura_m": 0.18
        },
        {
          "hora": "01:29",
          "altura_m": 0.26
        },
        {
          "hora": "00:19",
          "altura_m": 0.16
        }
      ]
    },
    {
      "data": "2025-10-15",
      "mares": [
        {
          "hora": "02:14",
          "altura_m": 0.21
        },
        {
          "hora": "00:25",
          "altura_m": 0.18
        }
      ]
    },
    {
      "data": "2025-11-01",
      "mares": [
        {
          "hora": "22:06",
          "altura_m": 0.3
        }
      ]
    },
    {
      "data": "2025-11-03",
      "mares": [
        {
          "hora": "08:08",
          "altura_m": 0.02
        },
        {
          "hora": "01:31",
          "altura_m": 0.36
        }
      ]
    },
    {
      "data": "2025-11-04",
      "mares": [
        {
          "hora": "00:47",
          "altura_m": 0.38
        },
        {
          "hora": "02:08",
          "altura_m": 0.36
        }
      ]
    },
    {
      "data": "2025-11-06",
      "mares": [
        {
          "hora": "04:59",
          "altura_m": 0.26
        },
        {
          "hora": "05:59",
          "altura_m": 0.24
        }
      ]
    },
    {
      "data": "2025-11-07",
      "mares": [
        {
          "hora": "00:04",
          "altura_m": 0.18
        },
        {
          "hora": "04:02",
          "altura_m": 0.3
        }
      ]
    },
    {
      "data": "2025-11-08",
      "mares": [
        {
          "hora": "01:04",
          "altura_m": 0.15
        },
        {
          "hora": "04:55",
          "altura_m": 0.29
        }
      ]
    },
    {
      "data": "2025-11-10",
      "mares": [
        {
          "hora": "06:12",
          "altura_m": 0.29
        },
        {
          "hora": "11:46",
          "altura_m": 0.44
        }
      ]
    },
    {
      "data": "2025-11-11",
      "mares": [
        {
          "hora": "00:25",
          "altura_m": 0.23
        },
        {
          "hora": "00:17",
          "altura_m": 0.12
        }
      ]
    },
    {
      "data": "2025-11-12",
      "mares": [
        {
          "hora": "01:12",
          "altura_m": 0.21
        },
        {
          "hora": "00:06",
          "altura_m": 0.16
        }
      ]
    },
    {
      "data": "2025-11-14",
      "mares": [
        {
          "hora": "02:59",
          "altura_m": 0.19
        },
        {
          "hora": "01:12",
          "altura_m": 0.23
        }
      ]
    },
    {
      "data": "2025-12-01",
      "mares": [
        {
          "hora": "23:38",
          "altura_m": 0.14
        }
      ]
    },
    {
      "data": "2025-12-03",
      "mares": [
        {
          "hora": "00:25",
          "altura_m": 0.38
        },
        {
          "hora": "02:02",
          "altura_m": 0.34
        }
      ]
    },
    {
      "data": "2025-12-04",
      "mares": [
        {
          "hora": "01:19",
          "altura_m": 0.4
        },
        {
          "hora": "02:44",
          "altura_m": 0.33
        }
      ]
    },
    {
      "data": "2025-12-06",
      "mares": [
        {
          "hora": "05:04",
          "altura_m": 0.31
        },
        {
          "hora": "06:01",
          "altura_m": 0.29
        }
      ]
    },
    {
      "data": "2025-12-07",
      "mares": [
        {
          "hora": "00:34",
          "altura_m": 0.07
        },
        {
          "hora": "04:53",
          "altura_m": 0.3
        }
      ]
    },
    {
      "data": "2025-12-08",
      "mares": [
        {
          "hora": "01:32",
          "altura_m": 0.05
        },
        {
          "hora": "10:44",
          "altura_m": 0.42
        }
      ]
    },
    {
      "data": "2025-12-10",
      "mares": [
        {
          "hora": "03:40",
          "altura_m": 0.05
        },
        {
          "hora": "07:53",
          "altura_m": 0.24
        }
      ]
    },
    {
      "data": "2025-12-11",
      "mares": [
        {
          "hora": "01:01",
          "altura_m": 0.21
        },
        {
          "hora": "00:04",
          "altura_m": 0.18
        }
      ]
    },
    {
      "data": "2025-12-12",
      "mares": [
        {
          "hora": "01:47",
          "altura_m": 0.23
        },
        {
          "hora": "00:53",
          "altura_m": 0.24
        }
      ]
    },
    {
      "data": "2025-12-14",
      "mares": [
        {
          "hora": "00:06",
          "altura_m": 0.18
        },
        {
          "hora": "02:40",
          "altura_m": 0.36
        }
      ]
    },
    {
      "data": "2025-12-16",
      "mares": [
        {
          "hora": "02:49",
          "altura_m": 0.26
        }
      ]
    }
  ]
}